CHANGES.rst
CONTRIBUTORS.rst
LICENSE
MANIFEST.in
README.rst
setup.py
src/edeposit/__init__.py
src/edeposit.amqp.calibre.egg-info/PKG-INFO
src/edeposit.amqp.calibre.egg-info/SOURCES.txt
src/edeposit.amqp.calibre.egg-info/dependency_links.txt
src/edeposit.amqp.calibre.egg-info/namespace_packages.txt
src/edeposit.amqp.calibre.egg-info/not-zip-safe
src/edeposit.amqp.calibre.egg-info/requires.txt
src/edeposit.amqp.calibre.egg-info/top_level.txt
src/edeposit/amqp/__init__.py
src/edeposit/amqp/calibre/__init__.py
src/edeposit/amqp/calibre/calibre.py
src/edeposit/amqp/calibre/tests/inspector.py
src/edeposit/amqp/calibre/tests/test_package.txt